MANIFEST.in
README.txt
setup.py
collective/__init__.py
collective.lcstartp.egg-info/PKG-INFO
collective.lcstartp.egg-info/SOURCES.txt
collective.lcstartp.egg-info/dependency_links.txt
collective.lcstartp.egg-info/entry_points.txt
collective.lcstartp.egg-info/namespace_packages.txt
collective.lcstartp.egg-info/not-zip-safe
collective.lcstartp.egg-info/requires.txt
collective.lcstartp.egg-info/top_level.txt
collective/lcstartp/__init__.py
collective/lcstartp/configure.zcml
collective/lcstartp/interfaces.py
collective/lcstartp/tests.py
collective/lcstartp/browser/__init__.py
collective/lcstartp/browser/configure.zcml
collective/lcstartp/browser/settings.py
collective/lcstartp/browser/startp.pt
collective/lcstartp/browser/startp.py
collective/lcstartp/profiles/default/browserlayer.xml
collective/lcstartp/profiles/default/controlpanel.xml
collective/lcstartp/profiles/default/metadata.xml
collective/lcstartp/profiles/default/registry.xml
docs/HISTORY.txt
docs/INSTALL.txt
docs/LICENSE.GPL
docs/LICENSE.txt