Metadata-Version: 1.0
Name: collective.lcstartp
Version: 0.1
Summary: Linkchecker start page
Home-page: https://github.com/cleder/collective.lcstartp
Author: Christian Ledermann
Author-email: christian.ledermann@gmail.com
License: GPL
Platform: UNKNOWN
Classifier: Framework :: Plone
Classifier: Programming Language :: Python
